MANIFEST.in
setup.py
Maliens.egg-info/PKG-INFO
Maliens.egg-info/SOURCES.txt
Maliens.egg-info/dependency_links.txt
Maliens.egg-info/requires.txt
Maliens.egg-info/top_level.txt
aliens/__init__.py
aliens/alien.py
aliens/alien_invasion.py
aliens/bullet.py
aliens/button.py
aliens/game_functions.py
aliens/game_stats.py
aliens/scoreboard.py
aliens/settings.py
aliens/ship.py
aliens/images/alien.bmp
aliens/images/ship.bmp