Metadata-Version: 1.0
Name: Maliens
Version: 0.5
Summary: Very Silly Alien Game
Home-page: UNKNOWN
Author: Mathew Capone
Author-email: mcapone2016@gmail.com
License: None
Platform: UNKNOWN
